README.md
setup.py
md_test_udacity_dsnd_prob/Binomialdistribution.py
md_test_udacity_dsnd_prob/Gaussiandistribution.py
md_test_udacity_dsnd_prob/Generaldistribution.py
md_test_udacity_dsnd_prob/__init__.py
md_test_udacity_dsnd_prob.egg-info/PKG-INFO
md_test_udacity_dsnd_prob.egg-info/SOURCES.txt
md_test_udacity_dsnd_prob.egg-info/dependency_links.txt
md_test_udacity_dsnd_prob.egg-info/not-zip-safe
md_test_udacity_dsnd_prob.egg-info/top_level.txt