Metadata-Version: 1.0
Name: md-test-udacity-dsnd-prob
Version: 0.1
Summary: Gaussian and Binominal distributions
Home-page: UNKNOWN
Author: Marcos D
Author-email: test@gmail.com
License: UNKNOWN
Platform: UNKNOWN
